miniocr/__init__.py
miniocr/ocr.py
miniocr-0.0.4.dist-info/METADATA
miniocr-0.0.4.dist-info/WHEEL
miniocr-0.0.4.dist-info/top_level.txt
miniocr-0.0.4.dist-info/RECORD
