Metadata-Version: 2.1
Name: miniocr
Version: 0.0.4
Summary: A small OCR package
Author-email: Enrike Nur <enrike.nur@gmail.com>
Project-URL: Homepage, https://github.com/w95/miniocr
Project-URL: Bug Tracker, https://github.com/w95/miniocr/issues
Classifier: Programming Language :: Python :: 3
Classifier: License :: OSI Approved :: MIT License
Classifier: Operating System :: OS Independent
Requires-Python: >=3.8
Requires-Dist: openai
Requires-Dist: aiohttp
Requires-Dist: aiofiles
Requires-Dist: pdf2image
Requires-Dist: python-pptx
Requires-Dist: Pillow
